README.md
setup.py
reflect_client/Client.py
reflect_client/__init__.py
reflect_client.egg-info/PKG-INFO
reflect_client.egg-info/SOURCES.txt
reflect_client.egg-info/dependency_links.txt
reflect_client.egg-info/requires.txt
reflect_client.egg-info/top_level.txt